pytest_infinity/infinity.py
pytest_infinity/infinity.tcss
pytest_infinity-1.0.0.dist-info/METADATA
pytest_infinity-1.0.0.dist-info/WHEEL
pytest_infinity-1.0.0.dist-info/entry_points.txt
pytest_infinity-1.0.0.dist-info/RECORD
