Metadata-Version: 2.1
Name: pytest-infinity
Version: 1.0.0
Summary: 
Author: Yuvalino
Author-email: yuvalino@gmail.com
Requires-Python: >=3.8,<4.0
Classifier: Programming Language :: Python :: 3
Classifier: Programming Language :: Python :: 3.8
Classifier: Programming Language :: Python :: 3.9
Classifier: Programming Language :: Python :: 3.10
Classifier: Programming Language :: Python :: 3.11
Classifier: Programming Language :: Python :: 3.12
Requires-Dist: flask (>=3.0.3,<4.0.0)
Requires-Dist: pytest (>=8.0.0,<9.0.0)
Requires-Dist: pytest-publish (>=1.2.0,<2.0.0)
Requires-Dist: pytest-xdist (>=3.6.1,<4.0.0)
Requires-Dist: pytest-xstress (>=1.0.1,<2.0.0)
Requires-Dist: textual (>=0.63.4,<0.64.0)
